boa/__init__.py
boa/builtins.py
boa/compiler.py
boa/util.py
boa/code/__init__.py
boa/code/action.py
boa/code/appcall.py
boa/code/ast_preprocess.py
boa/code/expression.py
boa/code/method.py
boa/code/module.py
boa/code/pyop.py
boa/code/pytoken.py
boa/code/vmtoken.py
boa/interop/BigInteger.py
boa/interop/SmartContract.py
boa/interop/VMOp.py
boa/interop/__init__.py
boa/interop/Ontology/Attribute.py
boa/interop/Ontology/Contract.py
boa/interop/Ontology/Header.py
boa/interop/Ontology/Native.py
boa/interop/Ontology/Runtime.py
boa/interop/Ontology/Transaction.py
boa/interop/Ontology/__init__.py
boa/interop/System/Action.py
boa/interop/System/App.py
boa/interop/System/Block.py
boa/interop/System/Blockchain.py
boa/interop/System/Contract.py
boa/interop/System/ExecutionEngine.py
boa/interop/System/Header.py
boa/interop/System/Runtime.py
boa/interop/System/Storage.py
boa/interop/System/StorageContext.py
boa/interop/System/Transaction.py
boa/interop/System/__init__.py
boa_test/__init__.py
boa_test/example/AddTest.py
boa_test/example/AddTest1.py
boa_test/example/AddTest2.py
boa_test/example/AddTest3.py
boa_test/example/AddTest4.py
boa_test/example/AddTestVoid.py
boa_test/example/AppendTest.py
boa_test/example/ArrayArgsTest.py
boa_test/example/ArrayRemoveTest.py
boa_test/example/ArrayReverseTest.py
boa_test/example/ArrayTest.py
boa_test/example/ArrayTest1.py
boa_test/example/ArrayTest2.py
boa_test/example/ArrayTest3.py
boa_test/example/ArrayTest4.py
boa_test/example/BinopTest.py
boa_test/example/BreakpointTest.py
boa_test/example/ByteArrayTest.py
boa_test/example/ByteArrayTest2.py
boa_test/example/ByteArrayTest3.py
boa_test/example/CompareInTest.py
boa_test/example/CompareTest0.py
boa_test/example/CompareTest1.py
boa_test/example/CompareTest2.py
boa_test/example/CompareTest3.py
boa_test/example/ConcatTest.py
boa_test/example/ConcatTest2.py
boa_test/example/DictTest1.py
boa_test/example/DictTest2.py
boa_test/example/DictTest3.py
boa_test/example/DictTest4.py
ont_boa-0.4.9.dist-info/LICENSE.md
ont_boa-0.4.9.dist-info/METADATA
ont_boa-0.4.9.dist-info/WHEEL
ont_boa-0.4.9.dist-info/top_level.txt
ont_boa-0.4.9.dist-info/RECORD
